{
  "角色": "九",
  "卡牌": {
    "斩击": {
      "type": "攻击",
      "cost": 1,
      "effect": "基于防御的伤害100%"
    },
    "刀背格挡": {
      "type": "技能",
      "cost": 1,
      "effect": "护盾100%"
    },
    "破碎": {
      "type": "攻击",
      "cost": 3,
      "effect": "基于防御的伤害350%焚烧：生成1张破碎Lv.1加入手牌"
    },
    "老练一击": {
      "type": "攻击",
      "cost": 1,
      "effect": "基于防御的伤害140%基于伤害的护盾20%1回合内消耗卡牌的伤害总量提升20%"
    },
    "致命一击": {
      "type": "攻击",
      "cost": 1,
      "effect": "基于防御的伤害140%手牌中费用最高的消耗卡牌每需要1点费用，即可使此卡伤害总量提升20%，消耗对应卡牌"
    },
    "逆转之刃": {
      "type": "强化",
      "cost": 0,
      "effect": "主动获得护盾时，锻刃1"
    },
    "斗志": {
      "type": "技能",
      "cost": 1,
      "effect": "发动1张手牌中费用最高的自身攻击卡牌，并将其消耗"
    }
  }
}